Paystackpy/__init__.py
Paystackpy/api/__init__.py
Paystackpy/api/paystack.py
Paystackpy/api/transaction.py
Aishapackageforpractice-2.0.0.dist-info/LICENSE
Aishapackageforpractice-2.0.0.dist-info/METADATA
Aishapackageforpractice-2.0.0.dist-info/WHEEL
Aishapackageforpractice-2.0.0.dist-info/top_level.txt
Aishapackageforpractice-2.0.0.dist-info/RECORD
