Metadata-Version: 2.1
Name: Aishapackageforpractice
Version: 2.0.0
Summary: A Python package designed to simplify and streamline Paystack API integration, enabling secure         online payment processing in your Python applications.
Home-page: https://github.com/NUCCASJNR/PaystackPy
Author: Al-Areef
Classifier: Programming Language :: Python :: 3
Classifier: License :: OSI Approved :: MIT License
Classifier: Operating System :: OS Independent
License-File: LICENSE
Requires-Dist: requests
